tinderbotz/LocationGuardExtension.crx
tinderbotz/__init__.py
tinderbotz/session.py
tinderbotz-1.2.dist-info/LICENSE.txt
tinderbotz-1.2.dist-info/METADATA
tinderbotz-1.2.dist-info/WHEEL
tinderbotz-1.2.dist-info/top_level.txt
tinderbotz-1.2.dist-info/RECORD
