Metadata-Version: 2.1
Name: tinderbotz
Version: 1.2
Summary: Tinder automated bot and data scraper
Home-page: https://github.com/frederikme/TinderBot
Author: Frederik Mees
Author-email: frederik.mees@gmail.com
License: MIT
Download-URL: https://github.com/frederikme/TinderBot/archive/1.2.tar.gz
Keywords: Tinder,Automation,bot
Platform: UNKNOWN
Classifier: Development Status :: 3 - Alpha
Classifier: Intended Audience :: Developers
Classifier: Topic :: Software Development :: Build Tools
Classifier: License :: OSI Approved :: MIT License
Classifier: Programming Language :: Python :: 3
Requires-Dist: selenium
Requires-Dist: webdriver-manager
